delta_merge_project/README.md
delta_merge_project/__init__.py
delta_merge_project/scd_lib.py
delta_merge_project-0.1.0.dist-info/METADATA
delta_merge_project-0.1.0.dist-info/WHEEL
delta_merge_project-0.1.0.dist-info/RECORD
